Metadata-Version: 2.4
Name: glyphx
Version: 1.2.10
Summary: "A next-gen Python plotting library with SVG-first rendering, interactivity, themes, and clean defaults — better than matplotlib.pyplot"
Home-page: https://glyphx.readthedocs.io/
Author: Kyle Koeller
License: MIT
Requires-Python: >=3.7
License-File: LICENSE
Requires-Dist: numpy>=1.21
Requires-Dist: pandas>=1.4.2
Requires-Dist: scipy>=1.7
Requires-Dist: cairosvg>=2.5
Requires-Dist: ipython>=7.0
Requires-Dist: ipywidgets>=8.1
Provides-Extra: docs
Requires-Dist: sphinx-astropy; extra == "docs"
Requires-Dist: matplotlib; extra == "docs"
Dynamic: license-file
